tcia_download_manager/__init__.py
tcia_download_manager/__main__.py
tcia_download_manager/gui.py
tcia_download_manager/gui_path.py
tcia_download_manager-0.0.1.dist-info/LICENSE
tcia_download_manager-0.0.1.dist-info/METADATA
tcia_download_manager-0.0.1.dist-info/WHEEL
tcia_download_manager-0.0.1.dist-info/entry_points.txt
tcia_download_manager-0.0.1.dist-info/top_level.txt
tcia_download_manager-0.0.1.dist-info/RECORD
