Metadata-Version: 2.1
Name: tcia-download-manager
Version: 0.0.1
Summary: A tool for downloading TCIA data.
Author-email: Justin Kirby <justin.kirby@nih.gov>
License: Apache Software License
Project-URL: Homepage, https://github.com/kirbyju/tcia_download_manager
Classifier: Programming Language :: Python :: 3
Classifier: License :: OSI Approved :: Apache Software License
Classifier: Operating System :: OS Independent
Requires-Python: >=3.11
License-File: LICENSE
Requires-Dist: pandas
Requires-Dist: requests
Requires-Dist: PyQt5
